best-practices.md
maup/__init__.py
maup/adjacencies.py
maup/assign.py
maup/crs.py
maup/indexed_geometries.py
maup/indices.py
maup/intersections.py
maup/normalize.py
maup/progress_bar.py
maup/repair.py
maup/smart_repair.py
maup-2.0.2.dist-info/LICENSE
maup-2.0.2.dist-info/METADATA
maup-2.0.2.dist-info/WHEEL
maup-2.0.2.dist-info/RECORD
