Metadata-Version: 2.1
Name: maup
Version: 2.0.2
Summary: The geospatial toolkit for redistricting data
License: MIT
Author: Metric Geometry and Gerrymandering Group
Author-email: dev@mggg.org
Requires-Python: >=3.9.0,<3.13.0
Classifier: License :: OSI Approved :: MIT License
Classifier: Operating System :: OS Independent
Classifier: Programming Language :: Python :: 3
Classifier: Programming Language :: Python :: 3.9
Classifier: Programming Language :: Python :: 3.10
Classifier: Programming Language :: Python :: 3.11
Classifier: Programming Language :: Python :: 3.12
Requires-Dist: Shapely (>=2.0.1,<3.0.0)
Requires-Dist: geopandas (>=0.14.0,<0.15.0)
Requires-Dist: numpy (>=1.23.0,<2.0.0)
Requires-Dist: pandas (>=2.1.2,<3.0.0)
Requires-Dist: tqdm (>=4.61.1,<5.0.0)
